OLD/AIzymes_013.py
OLD/AIzymes_014.py
OLD/AIzymes_015.py
OLD/FieldTools.py
OLD/LMPNN_submit.py
OLD/PMPNN_submit.py
OLD/TEST_REFACTOR.py
OLD/helper_001.py
OLD/helper_002.py
OLD/main_running_001.py
OLD/main_running_002.py
OLD/main_running_003.py
OLD/main_startup_001.py
OLD/plotting_001 Backup.py
OLD/plotting_001.py
OLD/test1_1.py
OLD/test2_2.py
OLD/test_wraper.py
OLD/untitled..py
aizymes/FieldTools.py
aizymes/__init__.py
aizymes/aizymes.py
aizymes/design_AlphaFold3_001.py
aizymes/design_Boltz_001.py
aizymes/design_Chai1_001.py
aizymes/design_ESMfold_001.py
aizymes/design_MDMin_001.py
aizymes/design_MPNN_001.py
aizymes/design_RosettaDesign_001.py
aizymes/design_RosettaRelax_001.py
aizymes/design_match_001.py
aizymes/helper_002.py
aizymes/helper_display_structures_001.py
aizymes/main_design_001.py
aizymes/main_running_003.py
aizymes/main_scripts_001.py
aizymes/main_startup_002.py
aizymes/plotting_002.py
aizymes/plotting_tree_001.py
aizymes/scoring_BioDC_001.py
aizymes/scoring_Null_001.py
aizymes/scoring_efields_001.py
aizymes/setup_system_001.py
aizymes-0.1.11.dist-info/licenses/LICENSE.txt
aizymes-0.1.11.dist-info/METADATA
aizymes-0.1.11.dist-info/WHEEL
aizymes-0.1.11.dist-info/top_level.txt
aizymes-0.1.11.dist-info/RECORD
