Metadata-Version: 2.4
Name: aizymes
Version: 0.1.11
Summary: A modular enzyme design platform
Author-email: Adrian Bunzel <adrian.bunzel@mpi-marburg.mpg.de>
Requires-Python: >=3.8
License-File: LICENSE.txt
Requires-Dist: numpy
Requires-Dist: pandas
Requires-Dist: biopython
Requires-Dist: scikit-learn
Requires-Dist: matplotlib
Dynamic: license-file
